{"actions": [{"COMMAND": null, "RESPONSE": null}, {"COMMAND": "[1694415300.493][INFO]: [641638e3a3683248e0a448af48d2ed48] COMMAND InitSession {\n   \"capabilities\": {\n      \"firstMatch\": [ {\n         \"browserName\": \"chrome\",\n         \"goog:chromeOptions\": {\n\n         }\n      } ]\n   },\n   \"desiredCapabilities\": {\n      \"browserName\": \"chrome\",\n      \"goog:chromeOptions\": {\n\n      }\n   }\n}\n", "RESPONSE": "[1694415302.001][INFO]: [641638e3a3683248e0a448af48d2ed48] RESPONSE InitSession {\n   \"capabilities\": {\n      \"acceptInsecureCerts\": false,\n      \"browserName\": \"chrome\",\n      \"browserVersion\": \"91.0.4472.77\",\n      \"chrome\": {\n         \"chromedriverVersion\": \"91.0.4472.19 (1bf021f248676a0b2ab3ee0561d83a59e424c23e-refs/branch-heads/4472@{#288})\",\n         \"userDataDir\": \"/tmp/.com.google.Chrome.M0XuMY\"\n      },\n      \"goog:chromeOptions\": {\n         \"debuggerAddress\": \"localhost:40375\"\n      },\n      \"networkConnectionEnabled\": false,\n      \"pageLoadStrategy\": \"normal\",\n      \"platformName\": \"linux\",\n      \"proxy\": {\n\n      },\n      \"setWindowRect\": true,\n      \"strictFileInteractability\": false,\n      \"timeouts\": {\n         \"implicit\": 0,\n         \"pageLoad\": 300000,\n         \"script\": 30000\n      },\n      \"unhandledPromptBehavior\": \"dismiss and notify\",\n      \"webauthn:extension:largeBlob\": true,\n      \"webauthn:virtualAuthenticators\": true\n   },\n   \"sessionId\": \"641638e3a3683248e0a448af48d2ed48\"\n}\n"}, {"COMMAND": "[1694415302.801][INFO]: [641638e3a3683248e0a448af48d2ed48] COMMAND MaximizeWindow {\n\n}\n", "RESPONSE": "[1694415302.910][INFO]: [641638e3a3683248e0a448af48d2ed48] RESPONSE MaximizeWindow {\n   \"height\": 1058,\n   \"width\": 1920,\n   \"x\": 0,\n   \"y\": 0\n}\n"}, {"COMMAND": "[1694415303.042][INFO]: [641638e3a3683248e0a448af48d2ed48] COMMAND SetTimeouts {\n   \"implicit\": 30000\n}\n", "RESPONSE": null}, {"COMMAND": "[1694415303.074][INFO]: [641638e3a3683248e0a448af48d2ed48] COMMAND GetUrl {\n\n}\n", "RESPONSE": "[1694415303.080][INFO]: [641638e3a3683248e0a448af48d2ed48] RESPONSE GetUrl \"data:,\"\n"}, {"COMMAND": "[1694415303.109][INFO]: [641638e3a3683248e0a448af48d2ed48] COMMAND Navigate {\n   \"url\": \"https://crio-qkart-frontend-qa.vercel.app/register\"\n}\n", "RESPONSE": "[1694415304.022][INFO]: [641638e3a3683248e0a448af48d2ed48] RESPONSE Navigate\n"}, {"COMMAND": "[1694415304.058][INFO]: [641638e3a3683248e0a448af48d2ed48] COMMAND FindElement {\n   \"using\": \"css selector\",\n   \"value\": \"#username\"\n}\n", "RESPONSE": "[1694415304.093][INFO]: [641638e3a3683248e0a448af48d2ed48] RESPONSE FindElement {\n   \"element-6066-11e4-a52e-4f735466cecf\": \"fc0306ce-830b-4e01-816e-c15ec1281b63\"\n}\n"}, {"COMMAND": "[1694415304.156][INFO]: [641638e3a3683248e0a448af48d2ed48] COMMAND TypeElement {\n   \"id\": \"fc0306ce-830b-4e01-816e-c15ec1281b63\",\n   \"text\": \"testUser_1694415304117\",\n   \"value\": [ \"t\", \"e\", \"s\", \"t\", \"U\", \"s\", \"e\", \"r\", \"_\", \"1\", \"6\", \"9\", \"4\", \"4\", \"1\", \"5\", \"3\", \"0\", \"4\", \"1\", \"1\", \"7\" ]\n}\n", "RESPONSE": "[1694415304.561][INFO]: [641638e3a3683248e0a448af48d2ed48] RESPONSE TypeElement\n"}, {"COMMAND": "[1694415304.581][INFO]: [641638e3a3683248e0a448af48d2ed48] COMMAND FindElement {\n   \"using\": \"css selector\",\n   \"value\": \"#password\"\n}\n", "RESPONSE": "[1694415304.594][INFO]: [641638e3a3683248e0a448af48d2ed48] RESPONSE FindElement {\n   \"element-6066-11e4-a52e-4f735466cecf\": \"dfb5240e-aac0-4dd3-8bf6-72af55d86ec7\"\n}\n"}, {"COMMAND": "[1694415304.622][INFO]: [641638e3a3683248e0a448af48d2ed48] COMMAND TypeElement {\n   \"id\": \"dfb5240e-aac0-4dd3-8bf6-72af55d86ec7\",\n   \"text\": \"abc@123\",\n   \"value\": [ \"a\", \"b\", \"c\", \"@\", \"1\", \"2\", \"3\" ]\n}\n", "RESPONSE": "[1694415304.851][INFO]: [641638e3a3683248e0a448af48d2ed48] RESPONSE TypeElement\n"}, {"COMMAND": "[1694415304.909][INFO]: [641638e3a3683248e0a448af48d2ed48] COMMAND FindElement {\n   \"using\": \"css selector\",\n   \"value\": \"#confirmPassword\"\n}\n", "RESPONSE": "[1694415304.932][INFO]: [641638e3a3683248e0a448af48d2ed48] RESPONSE FindElement {\n   \"element-6066-11e4-a52e-4f735466cecf\": \"a27de575-302f-45b0-8a5f-3c85b8ad7ec6\"\n}\n"}, {"COMMAND": "[1694415304.977][INFO]: [641638e3a3683248e0a448af48d2ed48] COMMAND TypeElement {\n   \"id\": \"a27de575-302f-45b0-8a5f-3c85b8ad7ec6\",\n   \"text\": \"abc@123\",\n   \"value\": [ \"a\", \"b\", \"c\", \"@\", \"1\", \"2\", \"3\" ]\n}\n", "RESPONSE": "[1694415305.212][INFO]: [641638e3a3683248e0a448af48d2ed48] RESPONSE TypeElement\n"}, {"COMMAND": "[1694415305.255][INFO]: [641638e3a3683248e0a448af48d2ed48] COMMAND FindElement {\n   \"using\": \"css selector\",\n   \"value\": \".button\"\n}\n", "RESPONSE": "[1694415305.274][INFO]: [641638e3a3683248e0a448af48d2ed48] RESPONSE FindElement {\n   \"element-6066-11e4-a52e-4f735466cecf\": \"7aab2744-bfc1-4530-a7e7-0613c2e985e6\"\n}\n"}, {"COMMAND": "[1694415305.310][INFO]: [641638e3a3683248e0a448af48d2ed48] COMMAND ClickElement {\n   \"id\": \"7aab2744-bfc1-4530-a7e7-0613c2e985e6\"\n}\n", "RESPONSE": "[1694415305.402][INFO]: [641638e3a3683248e0a448af48d2ed48] RESPONSE ClickElement\n"}, {"COMMAND": "[1694415308.421][INFO]: [641638e3a3683248e0a448af48d2ed48] COMMAND GetUrl {\n\n}\n", "RESPONSE": "[1694415308.429][INFO]: [641638e3a3683248e0a448af48d2ed48] RESPONSE GetUrl \"https://crio-qkart-frontend-qa.vercel.app/login\"\n"}, {"COMMAND": "[1694415308.457][INFO]: [641638e3a3683248e0a448af48d2ed48] COMMAND GetUrl {\n\n}\n", "RESPONSE": "[1694415308.461][INFO]: [641638e3a3683248e0a448af48d2ed48] RESPONSE GetUrl \"https://crio-qkart-frontend-qa.vercel.app/login\"\n"}, {"COMMAND": "[1694415308.481][INFO]: [641638e3a3683248e0a448af48d2ed48] COMMAND FindElement {\n   \"using\": \"css selector\",\n   \"value\": \"#username\"\n}\n", "RESPONSE": "[1694415308.495][INFO]: [641638e3a3683248e0a448af48d2ed48] RESPONSE FindElement {\n   \"element-6066-11e4-a52e-4f735466cecf\": \"96c4cdba-7693-4fc8-a41f-19063c81889a\"\n}\n"}, {"COMMAND": "[1694415308.519][INFO]: [641638e3a3683248e0a448af48d2ed48] COMMAND TypeElement {\n   \"id\": \"96c4cdba-7693-4fc8-a41f-19063c81889a\",\n   \"text\": \"testUser_1694415304117\",\n   \"value\": [ \"t\", \"e\", \"s\", \"t\", \"U\", \"s\", \"e\", \"r\", \"_\", \"1\", \"6\", \"9\", \"4\", \"4\", \"1\", \"5\", \"3\", \"0\", \"4\", \"1\", \"1\", \"7\" ]\n}\n", "RESPONSE": "[1694415308.946][INFO]: [641638e3a3683248e0a448af48d2ed48] RESPONSE TypeElement\n"}, {"COMMAND": "[1694415309.973][INFO]: [641638e3a3683248e0a448af48d2ed48] COMMAND FindElement {\n   \"using\": \"css selector\",\n   \"value\": \"#password\"\n}\n", "RESPONSE": "[1694415309.983][INFO]: [641638e3a3683248e0a448af48d2ed48] RESPONSE FindElement {\n   \"element-6066-11e4-a52e-4f735466cecf\": \"6a4eb54d-3137-43f5-a728-977597ac6b53\"\n}\n"}, {"COMMAND": "[1694415310.011][INFO]: [641638e3a3683248e0a448af48d2ed48] COMMAND TypeElement {\n   \"id\": \"6a4eb54d-3137-43f5-a728-977597ac6b53\",\n   \"text\": \"abc@123\",\n   \"value\": [ \"a\", \"b\", \"c\", \"@\", \"1\", \"2\", \"3\" ]\n}\n", "RESPONSE": "[1694415310.155][INFO]: [641638e3a3683248e0a448af48d2ed48] RESPONSE TypeElement\n"}, {"COMMAND": "[1694415310.182][INFO]: [641638e3a3683248e0a448af48d2ed48] COMMAND FindElement {\n   \"using\": \"xpath\",\n   \"value\": \"//body/div[@id='root']/div[1]/div[1]/div[2]/div[1]/button[1]\"\n}\n", "RESPONSE": "[1694415310.206][INFO]: [641638e3a3683248e0a448af48d2ed48] RESPONSE FindElement {\n   \"element-6066-11e4-a52e-4f735466cecf\": \"0671c242-e222-4d3e-b41a-03deb1c698c0\"\n}\n"}, {"COMMAND": "[1694415310.223][INFO]: [641638e3a3683248e0a448af48d2ed48] COMMAND ClickElement {\n   \"id\": \"0671c242-e222-4d3e-b41a-03deb1c698c0\"\n}\n", "RESPONSE": "[1694415310.306][INFO]: [641638e3a3683248e0a448af48d2ed48] RESPONSE ClickElement\n"}, {"COMMAND": "[1694415315.325][INFO]: [641638e3a3683248e0a448af48d2ed48] COMMAND FindElement {\n   \"using\": \"css selector\",\n   \"value\": \".username\\\\-text\"\n}\n", "RESPONSE": "[1694415315.343][INFO]: [641638e3a3683248e0a448af48d2ed48] RESPONSE FindElement {\n   \"element-6066-11e4-a52e-4f735466cecf\": \"f4762f14-b245-476b-b7d6-02a996afd8e1\"\n}\n"}, {"COMMAND": "[1694415315.357][INFO]: [641638e3a3683248e0a448af48d2ed48] COMMAND GetElementText {\n   \"id\": \"f4762f14-b245-476b-b7d6-02a996afd8e1\"\n}\n", "RESPONSE": "[1694415315.372][INFO]: [641638e3a3683248e0a448af48d2ed48] RESPONSE GetElementText \"testUser_1694415304117\"\n"}, {"COMMAND": "[1694415315.402][INFO]: [641638e3a3683248e0a448af48d2ed48] COMMAND FindElement {\n   \"using\": \"css selector\",\n   \"value\": \".MuiButton\\\\-text\"\n}\n", "RESPONSE": "[1694415315.414][INFO]: [641638e3a3683248e0a448af48d2ed48] RESPONSE FindElement {\n   \"element-6066-11e4-a52e-4f735466cecf\": \"d68bc40c-a22d-4fa2-8c87-7640494ff0ef\"\n}\n"}, {"COMMAND": "[1694415315.438][INFO]: [641638e3a3683248e0a448af48d2ed48] COMMAND ClickElement {\n   \"id\": \"d68bc40c-a22d-4fa2-8c87-7640494ff0ef\"\n}\n", "RESPONSE": "[1694415315.750][INFO]: [641638e3a3683248e0a448af48d2ed48] RESPONSE ClickElement\n"}, {"COMMAND": "[1694415318.766][INFO]: [641638e3a3683248e0a448af48d2ed48] COMMAND GetUrl {\n\n}\n", "RESPONSE": "[1694415318.770][INFO]: [641638e3a3683248e0a448af48d2ed48] RESPONSE GetUrl \"https://crio-qkart-frontend-qa.vercel.app/\"\n"}, {"COMMAND": "[1694415318.799][INFO]: [641638e3a3683248e0a448af48d2ed48] COMMAND Navigate {\n   \"url\": \"https://crio-qkart-frontend-qa.vercel.app/register\"\n}\n", "RESPONSE": "[1694415319.017][INFO]: [641638e3a3683248e0a448af48d2ed48] RESPONSE Navigate\n"}, {"COMMAND": "[1694415319.058][INFO]: [641638e3a3683248e0a448af48d2ed48] COMMAND FindElement {\n   \"using\": \"css selector\",\n   \"value\": \"#username\"\n}\n", "RESPONSE": "[1694415319.077][INFO]: [641638e3a3683248e0a448af48d2ed48] RESPONSE FindElement {\n   \"element-6066-11e4-a52e-4f735466cecf\": \"35cc7ff2-e3e7-4329-90d2-f446a753e968\"\n}\n"}, {"COMMAND": "[1694415319.110][INFO]: [641638e3a3683248e0a448af48d2ed48] COMMAND TypeElement {\n   \"id\": \"35cc7ff2-e3e7-4329-90d2-f446a753e968\",\n   \"text\": \"testUser_1694415319084\",\n   \"value\": [ \"t\", \"e\", \"s\", \"t\", \"U\", \"s\", \"e\", \"r\", \"_\", \"1\", \"6\", \"9\", \"4\", \"4\", \"1\", \"5\", \"3\", \"1\", \"9\", \"0\", \"8\", \"4\" ]\n}\n", "RESPONSE": "[1694415319.594][INFO]: [641638e3a3683248e0a448af48d2ed48] RESPONSE TypeElement\n"}, {"COMMAND": "[1694415319.611][INFO]: [641638e3a3683248e0a448af48d2ed48] COMMAND FindElement {\n   \"using\": \"css selector\",\n   \"value\": \"#password\"\n}\n", "RESPONSE": "[1694415319.620][INFO]: [641638e3a3683248e0a448af48d2ed48] RESPONSE FindElement {\n   \"element-6066-11e4-a52e-4f735466cecf\": \"acefeda7-5696-4bbc-9d83-996f2607ef2d\"\n}\n"}, {"COMMAND": "[1694415319.641][INFO]: [641638e3a3683248e0a448af48d2ed48] COMMAND TypeElement {\n   \"id\": \"acefeda7-5696-4bbc-9d83-996f2607ef2d\",\n   \"text\": \"abc@123\",\n   \"value\": [ \"a\", \"b\", \"c\", \"@\", \"1\", \"2\", \"3\" ]\n}\n", "RESPONSE": "[1694415319.762][INFO]: [641638e3a3683248e0a448af48d2ed48] RESPONSE TypeElement\n"}, {"COMMAND": "[1694415319.779][INFO]: [641638e3a3683248e0a448af48d2ed48] COMMAND FindElement {\n   \"using\": \"css selector\",\n   \"value\": \"#confirmPassword\"\n}\n", "RESPONSE": "[1694415319.792][INFO]: [641638e3a3683248e0a448af48d2ed48] RESPONSE FindElement {\n   \"element-6066-11e4-a52e-4f735466cecf\": \"cfb79209-5a9a-40fa-9705-6f52adebf975\"\n}\n"}, {"COMMAND": "[1694415319.810][INFO]: [641638e3a3683248e0a448af48d2ed48] COMMAND TypeElement {\n   \"id\": \"cfb79209-5a9a-40fa-9705-6f52adebf975\",\n   \"text\": \"abc@123\",\n   \"value\": [ \"a\", \"b\", \"c\", \"@\", \"1\", \"2\", \"3\" ]\n}\n", "RESPONSE": "[1694415319.953][INFO]: [641638e3a3683248e0a448af48d2ed48] RESPONSE TypeElement\n"}, {"COMMAND": "[1694415319.976][INFO]: [641638e3a3683248e0a448af48d2ed48] COMMAND FindElement {\n   \"using\": \"css selector\",\n   \"value\": \".button\"\n}\n", "RESPONSE": "[1694415319.989][INFO]: [641638e3a3683248e0a448af48d2ed48] RESPONSE FindElement {\n   \"element-6066-11e4-a52e-4f735466cecf\": \"759eff33-c9ad-4c92-bb66-b0166d0aa9aa\"\n}\n"}, {"COMMAND": "[1694415320.016][INFO]: [641638e3a3683248e0a448af48d2ed48] COMMAND ClickElement {\n   \"id\": \"759eff33-c9ad-4c92-bb66-b0166d0aa9aa\"\n}\n", "RESPONSE": "[1694415320.099][INFO]: [641638e3a3683248e0a448af48d2ed48] RESPONSE ClickElement\n"}, {"COMMAND": "[1694415323.115][INFO]: [641638e3a3683248e0a448af48d2ed48] COMMAND GetUrl {\n\n}\n", "RESPONSE": "[1694415323.120][INFO]: [641638e3a3683248e0a448af48d2ed48] RESPONSE GetUrl \"https://crio-qkart-frontend-qa.vercel.app/login\"\n"}, {"COMMAND": "[1694415323.141][INFO]: [641638e3a3683248e0a448af48d2ed48] COMMAND GetUrl {\n\n}\n", "RESPONSE": "[1694415323.155][INFO]: [641638e3a3683248e0a448af48d2ed48] RESPONSE GetUrl \"https://crio-qkart-frontend-qa.vercel.app/login\"\n"}, {"COMMAND": "[1694415323.211][INFO]: [641638e3a3683248e0a448af48d2ed48] COMMAND Navigate {\n   \"url\": \"https://crio-qkart-frontend-qa.vercel.app/register\"\n}\n", "RESPONSE": "[1694415323.478][INFO]: [641638e3a3683248e0a448af48d2ed48] RESPONSE Navigate\n"}, {"COMMAND": "[1694415323.506][INFO]: [641638e3a3683248e0a448af48d2ed48] COMMAND FindElement {\n   \"using\": \"css selector\",\n   \"value\": \"#username\"\n}\n", "RESPONSE": "[1694415323.520][INFO]: [641638e3a3683248e0a448af48d2ed48] RESPONSE FindElement {\n   \"element-6066-11e4-a52e-4f735466cecf\": \"5916c567-49fa-4e90-b2af-4b5e19817e7c\"\n}\n"}, {"COMMAND": "[1694415323.550][INFO]: [641638e3a3683248e0a448af48d2ed48] COMMAND TypeElement {\n   \"id\": \"5916c567-49fa-4e90-b2af-4b5e19817e7c\",\n   \"text\": \"testUser_1694415319084\",\n   \"value\": [ \"t\", \"e\", \"s\", \"t\", \"U\", \"s\", \"e\", \"r\", \"_\", \"1\", \"6\", \"9\", \"4\", \"4\", \"1\", \"5\", \"3\", \"1\", \"9\", \"0\", \"8\", \"4\" ]\n}\n", "RESPONSE": "[1694415324.065][INFO]: [641638e3a3683248e0a448af48d2ed48] RESPONSE TypeElement\n"}, {"COMMAND": "[1694415324.088][INFO]: [641638e3a3683248e0a448af48d2ed48] COMMAND FindElement {\n   \"using\": \"css selector\",\n   \"value\": \"#password\"\n}\n", "RESPONSE": "[1694415324.098][INFO]: [641638e3a3683248e0a448af48d2ed48] RESPONSE FindElement {\n   \"element-6066-11e4-a52e-4f735466cecf\": \"2e72d0bb-1565-4b69-840e-be9d8a4fc364\"\n}\n"}, {"COMMAND": "[1694415324.119][INFO]: [641638e3a3683248e0a448af48d2ed48] COMMAND TypeElement {\n   \"id\": \"2e72d0bb-1565-4b69-840e-be9d8a4fc364\",\n   \"text\": \"abc@123\",\n   \"value\": [ \"a\", \"b\", \"c\", \"@\", \"1\", \"2\", \"3\" ]\n}\n", "RESPONSE": "[1694415324.258][INFO]: [641638e3a3683248e0a448af48d2ed48] RESPONSE TypeElement\n"}, {"COMMAND": "[1694415324.284][INFO]: [641638e3a3683248e0a448af48d2ed48] COMMAND FindElement {\n   \"using\": \"css selector\",\n   \"value\": \"#confirmPassword\"\n}\n", "RESPONSE": "[1694415324.294][INFO]: [641638e3a3683248e0a448af48d2ed48] RESPONSE FindElement {\n   \"element-6066-11e4-a52e-4f735466cecf\": \"8e938d71-8e14-43b3-8b16-269a3bca3801\"\n}\n"}, {"COMMAND": "[1694415324.310][INFO]: [641638e3a3683248e0a448af48d2ed48] COMMAND TypeElement {\n   \"id\": \"8e938d71-8e14-43b3-8b16-269a3bca3801\",\n   \"text\": \"abc@123\",\n   \"value\": [ \"a\", \"b\", \"c\", \"@\", \"1\", \"2\", \"3\" ]\n}\n", "RESPONSE": "[1694415324.448][INFO]: [641638e3a3683248e0a448af48d2ed48] RESPONSE TypeElement\n"}, {"COMMAND": "[1694415324.470][INFO]: [641638e3a3683248e0a448af48d2ed48] COMMAND FindElement {\n   \"using\": \"css selector\",\n   \"value\": \".button\"\n}\n", "RESPONSE": "[1694415324.485][INFO]: [641638e3a3683248e0a448af48d2ed48] RESPONSE FindElement {\n   \"element-6066-11e4-a52e-4f735466cecf\": \"028bb91c-612c-433a-943a-93a275fd8dab\"\n}\n"}, {"COMMAND": "[1694415324.502][INFO]: [641638e3a3683248e0a448af48d2ed48] COMMAND ClickElement {\n   \"id\": \"028bb91c-612c-433a-943a-93a275fd8dab\"\n}\n", "RESPONSE": "[1694415324.586][INFO]: [641638e3a3683248e0a448af48d2ed48] RESPONSE ClickElement\n"}, {"COMMAND": "[1694415327.599][INFO]: [641638e3a3683248e0a448af48d2ed48] COMMAND GetUrl {\n\n}\n", "RESPONSE": "[1694415327.621][INFO]: [641638e3a3683248e0a448af48d2ed48] RESPONSE GetUrl \"https://crio-qkart-frontend-qa.vercel.app/register\"\n"}]}